huffman/Encodage.py
huffman/File.py
huffman/Frequency.py
huffman/Huffman.py
huffman/HuffmanInterface.py
huffman/Node.py
huffman/Ratio.py
huffman/Tree.py
huffman/__init__.py
huffman-project/Encodage.py
huffman-project/File.py
huffman-project/Frequency.py
huffman-project/Huffman.py
huffman-project/HuffmanInterface.py
huffman-project/Node.py
huffman-project/Ratio.py
huffman-project/Tree.py
huffman-project/__init__.py
huffman_project-0.2.2.dist-info/LICENSE
huffman_project-0.2.2.dist-info/METADATA
huffman_project-0.2.2.dist-info/WHEEL
huffman_project-0.2.2.dist-info/top_level.txt
huffman_project-0.2.2.dist-info/RECORD
