Metadata-Version: 2.1
Name: huffman-project
Version: 0.2.2
Summary: huffman-project package to reduce data based on character frequency
Home-page: https://github.com/M4verickFr/huffman-project
Author: Maverick Perrollaz
Author-email: maverick.perrollaz@pm.me
License: Apache 2 License
Platform: UNKNOWN
Classifier: Development Status :: 3 - Alpha
Classifier: Topic :: Utilities
Classifier: License :: OSI Approved :: Apache Software License
Classifier: Programming Language :: Python :: 3
Classifier: Programming Language :: Python :: 3.4
Classifier: Programming Language :: Python :: 3.5
Classifier: Programming Language :: Python :: 3.6
